__init__.py
glucid8824.py
glucid/Glucid8824_UI.py
glucid/Glucid8824_rc.py
glucid/__init__.py
glucid/glucid.py
glucid/glucid8824.py
glucid/glucid_cli.py
glucid/xglucid.py
glucid/xglucidUIWidgets.py
glucid8824/__init__.py
glucid8824/glucid8824.py
glucid-0.5.1.dist-info/LICENSE.txt
glucid-0.5.1.dist-info/METADATA
glucid-0.5.1.dist-info/WHEEL
glucid-0.5.1.dist-info/entry_points.txt
glucid-0.5.1.dist-info/top_level.txt
glucid-0.5.1.dist-info/RECORD
