Metadata-Version: 2.1
Name: glucid
Version: 0.5.1
Summary: Configure the Lucid 8824 AD/DA Audio Interface via              a Serial Connection
Home-page: http://github.com/danmechanic/glucid
Author: Daniel R Mechanic
Author-email: dan.mechanic@gmail.com
License: GPL V3
Project-URL: Author, http://www.danmechanic.com/
Project-URL: Source, https://github.com/danmechanic/glucid/
Keywords: lucid 8824 audio converter
Platform: UNKNOWN
Classifier: Development Status :: 3 - Alpha
Classifier: Programming Language :: Python :: 3
Classifier: Programming Language :: Python :: 3.2
Classifier: Programming Language :: Python :: 3.3
Classifier: Programming Language :: Python :: 3.4
Classifier: License :: OSI Approved :: GNU General Public License v3 (GPLv3)
Classifier: Topic :: Multimedia :: Sound/Audio :: Conversion
Classifier: Topic :: Multimedia :: Sound/Audio :: Capture/Recording
Requires-Python: >=3
Requires-Dist: PyQt5 (>=5.9)
Requires-Dist: PySerial
